noodle_quiz/__init__.py
noodle_quiz/answer_types.py
noodle_quiz/exc.py
noodle_quiz/question_types.py
noodle_quiz-0.1.3.dist-info/LICENSE
noodle_quiz-0.1.3.dist-info/METADATA
noodle_quiz-0.1.3.dist-info/WHEEL
noodle_quiz-0.1.3.dist-info/top_level.txt
noodle_quiz-0.1.3.dist-info/RECORD
