Metadata-Version: 2.1
Name: noodle-quiz
Version: 0.1.3
Summary: Noodle-Quiz (Not Moodle Quiz generator) is a set of utilities to generate quizzes for Moodle
Home-page: https://github.com/Epithumia/noodle-quiz
Author: Epithumia
Author-email: rafael.lopez@universite-paris-saclay.fr
License: MIT
Classifier: Development Status :: 3 - Alpha
Classifier: License :: OSI Approved :: MIT License
Classifier: Programming Language :: Python :: 3.10
License-File: LICENSE
